streamlit_cardselectable/__init__.py
streamlit_cardselectable/frontend/build/asset-manifest.json
streamlit_cardselectable/frontend/build/bootstrap.min.css
streamlit_cardselectable/frontend/build/index.html
streamlit_cardselectable/frontend/build/precache-manifest.0503201d1e5ade073cd1dfe604cec24d.js
streamlit_cardselectable/frontend/build/service-worker.js
streamlit_cardselectable/frontend/build/styles.css
streamlit_cardselectable/frontend/build/static/js/2.6d5d4386.chunk.js
streamlit_cardselectable/frontend/build/static/js/2.6d5d4386.chunk.js.LICENSE.txt
streamlit_cardselectable/frontend/build/static/js/2.6d5d4386.chunk.js.map
streamlit_cardselectable/frontend/build/static/js/main.8c9573d2.chunk.js
streamlit_cardselectable/frontend/build/static/js/main.8c9573d2.chunk.js.map
streamlit_cardselectable/frontend/build/static/js/runtime-main.ef4c9d3e.js
streamlit_cardselectable/frontend/build/static/js/runtime-main.ef4c9d3e.js.map
streamlit_cardselectable-0.0.4.dist-info/LICENSE
streamlit_cardselectable-0.0.4.dist-info/METADATA
streamlit_cardselectable-0.0.4.dist-info/WHEEL
streamlit_cardselectable-0.0.4.dist-info/top_level.txt
streamlit_cardselectable-0.0.4.dist-info/RECORD
