Metadata-Version: 2.1
Name: streamlit-cardselectable
Version: 0.0.4
Summary: Card that the user can select one of the available options. It was created as an alternative to the radio button.
Home-page: https://github.com/Mathtzt/st_cardselectable
Author: Matheus Ferreira
Author-email: matheus.cn10@gmail.com
License: UNKNOWN
Platform: UNKNOWN
Requires-Python: >=3.9
